setup.cfg
setup.py
karatsuba/__init__.py
karatsuba/py2.py
karatsuba/py3.py
karatsuba.egg-info/PKG-INFO
karatsuba.egg-info/SOURCES.txt
karatsuba.egg-info/dependency_links.txt
karatsuba.egg-info/top_level.txt