Metadata-Version: 1.0
Name: karatsuba
Version: 0.1.1
Summary: Fast convolution algorithms with Python types
Home-page: https://github.com/baruchel/karatsuba
Author: Thomas Baruchel
Author-email: baruchel@gmx.com
License: MIT
Platform: UNKNOWN
